{"units": {"cpu": "mcores", "cost/t": "usd/h", "workload": "req/h", "mem": "GiB"}, "system": {"apps": {"app_0": {"name": "app_0", "sfmpl": 1.0}}, "families": {"c5_m5_r5": [], "c5": ["c5_m5_r5"], "m5": ["c5_m5_r5"], "r5": ["c5_m5_r5"]}, "instance_classes": {"c5.large": {"cores": 1000.0, "mem": 4, "price": 0.096, "family": "c5"}, "c5.xlarge": {"cores": 2000.0, "mem": 8, "price": 0.192, "family": "c5"}, "c5.2xlarge": {"cores": 4000.0, "mem": 16, "price": 0.384, "family": "c5"}, "c5.4xlarge": {"cores": 8000.0, "mem": 32, "price": 0.768, "family": "c5"}, "c5.9xlarge": {"cores": 18000.0, "mem": 72, "price": 1.728, "family": "c5"}, "c5.12xlarge": {"cores": 24000.0, "mem": 96, "price": 2.3040000000000003, "family": "c5"}, "c5.18xlarge": {"cores": 36000.0, "mem": 144, "price": 3.456, "family": "c5"}, "c5.24xlarge": {"cores": 48000.0, "mem": 192, "price": 4.6080000000000005, "family": "c5"}, "m5.large": {"cores": 1000.0, "mem": 8, "price": 0.107, "family": "m5"}, "m5.xlarge": {"cores": 2000.0, "mem": 16, "price": 0.214, "family": "m5"}, "m5.2xlarge": {"cores": 4000.0, "mem": 32, "price": 0.428, "family": "m5"}, "m5.4xlarge": {"cores": 8000.0, "mem": 64, "price": 0.856, "family": "m5"}, "m5.9xlarge": {"cores": 18000.0, "mem": 144, "price": 1.926, "family": "m5"}, "m5.12xlarge": {"cores": 24000.0, "mem": 192, "price": 2.568, "family": "m5"}, "m5.18xlarge": {"cores": 36000.0, "mem": 288, "price": 3.852, "family": "m5"}, "m5.24xlarge": {"cores": 48000.0, "mem": 384, "price": 5.136, "family": "m5"}, "r5.large": {"cores": 1000.0, "mem": 16, "price": 0.141, "family": "r5"}, "r5.xlarge": {"cores": 2000.0, "mem": 32, "price": 0.282, "family": "r5"}, "r5.2xlarge": {"cores": 4000.0, "mem": 64, "price": 0.564, "family": "r5"}, "r5.4xlarge": {"cores": 8000.0, "mem": 128, "price": 1.128, "family": "r5"}, "r5.9xlarge": {"cores": 18000.0, "mem": 288, "price": 2.538, "family": "r5"}, "r5.12xlarge": {"cores": 24000.0, "mem": 384, "price": 3.3839999999999995, "family": "r5"}, "r5.18xlarge": {"cores": 36000.0, "mem": 576, "price": 5.076, "family": "r5"}, "r5.24xlarge": {"cores": 48000.0, "mem": 768, "price": 6.767999999999999, "family": "r5"}}, "perf": {"(app_0, c5_m5_r5)": {"cores": 97.19999999999999, "mem": [0.5831999999999999, 0.5831999999999999, 0.5831999999999999, 0.5831999999999999], "aggs": [1, 2, 4, 8], "maxagg": 8, "perf": 414.72}}}, "workloads": {"app_0": 3600.0}}