{"units": {"cpu": "mcores", "cost/t": "usd/h", "workload": "req/h", "mem": "GiB"}, "system": {"apps": {"app_0": {"name": "app_0", "sfmpl": 1.0}, "app_1": {"name": "app_1", "sfmpl": 1.0}, "app_2": {"name": "app_2", "sfmpl": 1.0}, "app_3": {"name": "app_3", "sfmpl": 1.0}, "app_4": {"name": "app_4", "sfmpl": 1.0}, "app_5": {"name": "app_5", "sfmpl": 1.0}, "app_6": {"name": "app_6", "sfmpl": 1.0}, "app_7": {"name": "app_7", "sfmpl": 1.0}, "app_8": {"name": "app_8", "sfmpl": 1.0}, "app_9": {"name": "app_9", "sfmpl": 1.0}, "app_10": {"name": "app_10", "sfmpl": 1.0}, "app_11": {"name": "app_11", "sfmpl": 1.0}, "app_12": {"name": "app_12", "sfmpl": 1.0}, "app_13": {"name": "app_13", "sfmpl": 1.0}, "app_14": {"name": "app_14", "sfmpl": 1.0}}, "families": {"c5_m5_r5": [], "c6i_m6i_r6i": [], "c6g_m6g_r6g": [], "c7a_m7a_r7a": [], "c5": ["c5_m5_r5"], "m5": ["c5_m5_r5"], "r5": ["c5_m5_r5"], "c6i": ["c6i_m6i_r6i"], "c6g": ["c6g_m6g_r6g"], "m6g": ["c6g_m6g_r6g"], "r6g": ["c6g_m6g_r6g"], "c7a": ["c7a_m7a_r7a"], "m7a": ["c7a_m7a_r7a"], "r7a": ["c7a_m7a_r7a"]}, "instance_classes": {"c5.large": {"cores": 1000.0, "mem": 4, "price": 0.096, "family": "c5"}, "c5.xlarge": {"cores": 2000.0, "mem": 8, "price": 0.192, "family": "c5"}, "c5.2xlarge": {"cores": 4000.0, "mem": 16, "price": 0.384, "family": "c5"}, "c5.4xlarge": {"cores": 8000.0, "mem": 32, "price": 0.768, "family": "c5"}, "c5.9xlarge": {"cores": 18000.0, "mem": 72, "price": 1.728, "family": "c5"}, "c5.12xlarge": {"cores": 24000.0, "mem": 96, "price": 2.3040000000000003, "family": "c5"}, "c5.18xlarge": {"cores": 36000.0, "mem": 144, "price": 3.456, "family": "c5"}, "c5.24xlarge": {"cores": 48000.0, "mem": 192, "price": 4.6080000000000005, "family": "c5"}, "m5.large": {"cores": 1000.0, "mem": 8, "price": 0.107, "family": "m5"}, "m5.xlarge": {"cores": 2000.0, "mem": 16, "price": 0.214, "family": "m5"}, "m5.2xlarge": {"cores": 4000.0, "mem": 32, "price": 0.428, "family": "m5"}, "m5.4xlarge": {"cores": 8000.0, "mem": 64, "price": 0.856, "family": "m5"}, "m5.9xlarge": {"cores": 18000.0, "mem": 144, "price": 1.926, "family": "m5"}, "m5.12xlarge": {"cores": 24000.0, "mem": 192, "price": 2.568, "family": "m5"}, "m5.18xlarge": {"cores": 36000.0, "mem": 288, "price": 3.852, "family": "m5"}, "m5.24xlarge": {"cores": 48000.0, "mem": 384, "price": 5.136, "family": "m5"}, "r5.large": {"cores": 1000.0, "mem": 16, "price": 0.141, "family": "r5"}, "r5.xlarge": {"cores": 2000.0, "mem": 32, "price": 0.282, "family": "r5"}, "r5.2xlarge": {"cores": 4000.0, "mem": 64, "price": 0.564, "family": "r5"}, "r5.4xlarge": {"cores": 8000.0, "mem": 128, "price": 1.128, "family": "r5"}, "r5.9xlarge": {"cores": 18000.0, "mem": 288, "price": 2.538, "family": "r5"}, "r5.12xlarge": {"cores": 24000.0, "mem": 384, "price": 3.3839999999999995, "family": "r5"}, "r5.18xlarge": {"cores": 36000.0, "mem": 576, "price": 5.076, "family": "r5"}, "r5.24xlarge": {"cores": 48000.0, "mem": 768, "price": 6.767999999999999, "family": "r5"}, "c6i.large": {"cores": 1000.0, "mem": 4, "price": 0.0912, "family": "c6i"}, "c6i.xlarge": {"cores": 2000.0, "mem": 8, "price": 0.1824, "family": "c6i"}, "c6i.2xlarge": {"cores": 4000.0, "mem": 16, "price": 0.3648, "family": "c6i"}, "c6i.4xlarge": {"cores": 8000.0, "mem": 32, "price": 0.7296, "family": "c6i"}, "c6i.8xlarge": {"cores": 16000.0, "mem": 64, "price": 1.4592, "family": "c6i"}, "c6i.12xlarge": {"cores": 24000.0, "mem": 96, "price": 2.1888, "family": "c6i"}, "c6i.16xlarge": {"cores": 32000.0, "mem": 128, "price": 2.9184, "family": "c6i"}, "c6i.24xlarge": {"cores": 48000.0, "mem": 192, "price": 4.3776, "family": "c6i"}, "c6i.32xlarge": {"cores": 64000.0, "mem": 256, "price": 5.8368, "family": "c6i"}, "m6i.large": {"cores": 1000.0, "mem": 8, "price": 0.107, "family": "c6i"}, "m6i.xlarge": {"cores": 2000.0, "mem": 16, "price": 0.214, "family": "c6i"}, "m6i.2xlarge": {"cores": 4000.0, "mem": 32, "price": 0.428, "family": "c6i"}, "m6i.4xlarge": {"cores": 8000.0, "mem": 64, "price": 0.856, "family": "c6i"}, "m6i.8xlarge": {"cores": 16000.0, "mem": 128, "price": 1.712, "family": "c6i"}, "m6i.12xlarge": {"cores": 24000.0, "mem": 192, "price": 2.568, "family": "c6i"}, "m6i.16xlarge": {"cores": 32000.0, "mem": 256, "price": 3.424, "family": "c6i"}, "m6i.24xlarge": {"cores": 48000.0, "mem": 384, "price": 5.136, "family": "c6i"}, "m6i.32xlarge": {"cores": 64000.0, "mem": 512, "price": 6.848, "family": "c6i"}, "r6i.large": {"cores": 1000.0, "mem": 16, "price": 0.141, "family": "c6i"}, "r6i.xlarge": {"cores": 2000.0, "mem": 32, "price": 0.282, "family": "c6i"}, "r6i.2xlarge": {"cores": 4000.0, "mem": 64, "price": 0.564, "family": "c6i"}, "r6i.4xlarge": {"cores": 8000.0, "mem": 128, "price": 1.128, "family": "c6i"}, "r6i.8xlarge": {"cores": 16000.0, "mem": 256, "price": 2.256, "family": "c6i"}, "r6i.12xlarge": {"cores": 24000.0, "mem": 384, "price": 3.3839999999999995, "family": "c6i"}, "r6i.16xlarge": {"cores": 24000.0, "mem": 384, "price": 3.3839999999999995, "family": "c6i"}, "r6i.24xlarge": {"cores": 48000.0, "mem": 768, "price": 6.767999999999999, "family": "c6i"}, "r6i.32xlarge": {"cores": 64000.0, "mem": 1024, "price": 9.024, "family": "c6i"}, "c6g.large": {"cores": 1000.0, "mem": 4, "price": 0.073, "family": "c6g"}, "c6g.xlarge": {"cores": 2000.0, "mem": 8, "price": 0.146, "family": "c6g"}, "c6g.2xlarge": {"cores": 4000.0, "mem": 16, "price": 0.292, "family": "c6g"}, "c6g.4xlarge": {"cores": 8000.0, "mem": 32, "price": 0.584, "family": "c6g"}, "c6g.9xlarge": {"cores": 18000.0, "mem": 72, "price": 1.3139999999999998, "family": "c6g"}, "c6g.12xlarge": {"cores": 24000.0, "mem": 96, "price": 1.7519999999999998, "family": "c6g"}, "c6g.18xlarge": {"cores": 36000.0, "mem": 144, "price": 2.6279999999999997, "family": "c6g"}, "c6g.24xlarge": {"cores": 48000.0, "mem": 192, "price": 3.5039999999999996, "family": "c6g"}, "m6g.large": {"cores": 1000.0, "mem": 8, "price": 0.086, "family": "m6g"}, "m6g.xlarge": {"cores": 2000.0, "mem": 16, "price": 0.172, "family": "m6g"}, "m6g.2xlarge": {"cores": 4000.0, "mem": 32, "price": 0.344, "family": "m6g"}, "m6g.4xlarge": {"cores": 8000.0, "mem": 64, "price": 0.688, "family": "m6g"}, "m6g.9xlarge": {"cores": 18000.0, "mem": 144, "price": 1.5479999999999998, "family": "m6g"}, "m6g.12xlarge": {"cores": 24000.0, "mem": 192, "price": 2.064, "family": "m6g"}, "m6g.18xlarge": {"cores": 36000.0, "mem": 288, "price": 3.0959999999999996, "family": "m6g"}, "m6g.24xlarge": {"cores": 48000.0, "mem": 384, "price": 4.128, "family": "m6g"}, "r6g.large": {"cores": 1000.0, "mem": 16, "price": 0.1128, "family": "r6g"}, "r6g.xlarge": {"cores": 2000.0, "mem": 32, "price": 0.2256, "family": "r6g"}, "r6g.2xlarge": {"cores": 4000.0, "mem": 64, "price": 0.4512, "family": "r6g"}, "r6g.4xlarge": {"cores": 8000.0, "mem": 128, "price": 0.9024, "family": "r6g"}, "r6g.9xlarge": {"cores": 18000.0, "mem": 288, "price": 2.0303999999999998, "family": "r6g"}, "r6g.12xlarge": {"cores": 24000.0, "mem": 384, "price": 2.7072, "family": "r6g"}, "r6g.18xlarge": {"cores": 36000.0, "mem": 576, "price": 4.0607999999999995, "family": "r6g"}, "r6g.24xlarge": {"cores": 48000.0, "mem": 768, "price": 5.4144, "family": "r6g"}, "c7a.large": {"cores": 1000.0, "mem": 4, "price": 0.11012, "family": "c7a"}, "c7a.xlarge": {"cores": 2000.0, "mem": 8, "price": 0.22024, "family": "c7a"}, "c7a.2xlarge": {"cores": 4000.0, "mem": 16, "price": 0.44048, "family": "c7a"}, "c7a.4xlarge": {"cores": 8000.0, "mem": 32, "price": 0.88096, "family": "c7a"}, "c7a.8xlarge": {"cores": 16000.0, "mem": 64, "price": 1.76192, "family": "c7a"}, "c7a.12xlarge": {"cores": 24000.0, "mem": 96, "price": 2.64288, "family": "c7a"}, "c7a.16xlarge": {"cores": 32000.0, "mem": 128, "price": 3.52384, "family": "c7a"}, "c7a.24xlarge": {"cores": 48000.0, "mem": 192, "price": 5.28576, "family": "c7a"}, "c7a.32xlarge": {"cores": 64000.0, "mem": 256, "price": 7.04768, "family": "c7a"}, "c7a.48xlarge": {"cores": 96000.0, "mem": 384, "price": 10.57152, "family": "c7a"}, "m7a.large": {"cores": 1000.0, "mem": 8, "price": 0.1292, "family": "m7a"}, "m7a.xlarge": {"cores": 2000.0, "mem": 16, "price": 0.2584, "family": "m7a"}, "m7a.2xlarge": {"cores": 4000.0, "mem": 32, "price": 0.5168, "family": "m7a"}, "m7a.4xlarge": {"cores": 8000.0, "mem": 64, "price": 1.0336, "family": "m7a"}, "m7a.8xlarge": {"cores": 16000.0, "mem": 128, "price": 2.0672, "family": "m7a"}, "m7a.12xlarge": {"cores": 24000.0, "mem": 192, "price": 3.1008000000000004, "family": "m7a"}, "m7a.16xlarge": {"cores": 32000.0, "mem": 256, "price": 4.1344, "family": "m7a"}, "m7a.24xlarge": {"cores": 48000.0, "mem": 384, "price": 6.201600000000001, "family": "m7a"}, "m7a.32xlarge": {"cores": 64000.0, "mem": 512, "price": 8.2688, "family": "m7a"}, "m7a.48xlarge": {"cores": 96000.0, "mem": 768, "price": 12.403200000000002, "family": "m7a"}, "r7a.large": {"cores": 1000.0, "mem": 16, "price": 0.17026, "family": "r7a"}, "r7a.xlarge": {"cores": 2000.0, "mem": 32, "price": 0.34052, "family": "r7a"}, "r7a.2xlarge": {"cores": 4000.0, "mem": 64, "price": 0.68104, "family": "r7a"}, "r7a.4xlarge": {"cores": 8000.0, "mem": 128, "price": 1.36208, "family": "r7a"}, "r7a.8xlarge": {"cores": 16000.0, "mem": 256, "price": 2.72416, "family": "r7a"}, "r7a.12xlarge": {"cores": 24000.0, "mem": 384, "price": 4.08624, "family": "r7a"}, "r7a.16xlarge": {"cores": 32000.0, "mem": 512, "price": 5.44832, "family": "r7a"}, "r7a.24xlarge": {"cores": 48000.0, "mem": 768, "price": 8.17248, "family": "r7a"}, "r7a.32xlarge": {"cores": 64000.0, "mem": 1024, "price": 10.89664, "family": "r7a"}, "r7a.48xlarge": {"cores": 96000.0, "mem": 1536, "price": 16.34496, "family": "r7a"}}, "perf": {"(app_0, c5_m5_r5)": {"cores": 8000.0, "mem": [7.34991780821918, 7.34991780821918], "aggs": [1, 2], "maxagg": 2, "perf": 534.2608695652174}, "(app_1, c5_m5_r5)": {"cores": 4000.0, "mem": [7.669479452054796, 7.669479452054796], "aggs": [1, 2], "maxagg": 2, "perf": 4480.0}, "(app_2, c5_m5_r5)": {"cores": 4000.0, "mem": [6.391232876712331, 6.391232876712331], "aggs": [1, 2], "maxagg": 2, "perf": 85.33333333333331}, "(app_3, c5_m5_r5)": {"cores": 4000.0, "mem": [6.39123287671233, 6.39123287671233], "aggs": [1, 2], "maxagg": 2, "perf": 307.2}, "(app_4, c5_m5_r5)": {"cores": 8000.0, "mem": [9.799890410958906, 9.799890410958906], "aggs": [1, 2], "maxagg": 2, "perf": 1068.5217391304348}, "(app_5, c5_m5_r5)": {"cores": 4000.0, "mem": [4.793424657534247, 4.793424657534247], "aggs": [1, 2], "maxagg": 2, "perf": 204.79999999999998}, "(app_6, c5_m5_r5)": {"cores": 8000.0, "mem": [7.34991780821918, 7.34991780821918], "aggs": [1, 2], "maxagg": 2, "perf": 7012.173913043479}, "(app_7, c5_m5_r5)": {"cores": 8000.0, "mem": [6.124931506849316, 6.124931506849316], "aggs": [1, 2], "maxagg": 2, "perf": 13356.521739130436}, "(app_8, c5_m5_r5)": {"cores": 4000.0, "mem": [4.793424657534248, 4.793424657534248], "aggs": [1, 2], "maxagg": 2, "perf": 170.66666666666663}, "(app_9, c5_m5_r5)": {"cores": 8000.0, "mem": [9.391561643835617, 9.391561643835617], "aggs": [1, 2], "maxagg": 2, "perf": 133.56521739130434}, "(app_10, c5_m5_r5)": {"cores": 4000.0, "mem": [3.994520547945206, 3.994520547945206], "aggs": [1, 2], "maxagg": 2, "perf": 102.39999999999999}, "(app_11, c5_m5_r5)": {"cores": 4000.0, "mem": [5.752109589041098, 5.752109589041098], "aggs": [1, 2], "maxagg": 2, "perf": 170.66666666666663}, "(app_12, c5_m5_r5)": {"cores": 4000.0, "mem": [6.39123287671233, 6.39123287671233], "aggs": [1, 2], "maxagg": 2, "perf": 76.8}, "(app_13, c5_m5_r5)": {"cores": 4000.0, "mem": [3.994520547945206, 3.994520547945206], "aggs": [1, 2], "maxagg": 2, "perf": 10240.0}, "(app_14, c5_m5_r5)": {"cores": 4000.0, "mem": [5.326027397260274, 5.326027397260274], "aggs": [1, 2], "maxagg": 2, "perf": 614.4}, "(app_0, c6i_m6i_r6i)": {"cores": 4000.0, "mem": [9.30989589041096, 9.30989589041096], "aggs": [1, 2], "maxagg": 2, "perf": 3506.0869565217395}, "(app_1, c6i_m6i_r6i)": {"cores": 4000.0, "mem": [6.071671232876714, 6.071671232876714], "aggs": [1, 2], "maxagg": 2, "perf": 1706.666666666667}, "(app_2, c6i_m6i_r6i)": {"cores": 4000.0, "mem": [6.98242191780822, 6.98242191780822], "aggs": [1, 2], "maxagg": 2, "perf": 534.2608695652174}, "(app_3, c6i_m6i_r6i)": {"cores": 4000.0, "mem": [6.071671232876713, 6.071671232876713], "aggs": [1, 2], "maxagg": 2, "perf": 1024.0000000000002}, "(app_4, c6i_m6i_r6i)": {"cores": 8000.0, "mem": [6.071671232876714, 6.071671232876714], "aggs": [1, 2], "maxagg": 2, "perf": 128.0}, "(app_5, c6i_m6i_r6i)": {"cores": 4000.0, "mem": [3.7947945205479456, 3.7947945205479456], "aggs": [1, 2], "maxagg": 2, "perf": 10240.0}, "(app_6, c6i_m6i_r6i)": {"cores": 4000.0, "mem": [5.059726027397261, 5.059726027397261], "aggs": [1, 2], "maxagg": 2, "perf": 7680.0}, "(app_7, c6i_m6i_r6i)": {"cores": 4000.0, "mem": [6.98242191780822, 6.98242191780822], "aggs": [1, 2], "maxagg": 2, "perf": 66.78260869565217}, "(app_8, c6i_m6i_r6i)": {"cores": 4000.0, "mem": [4.553753424657535, 4.553753424657535], "aggs": [1, 2], "maxagg": 2, "perf": 682.6666666666666}, "(app_9, c6i_m6i_r6i)": {"cores": 4000.0, "mem": [8.921983561643836, 8.921983561643836], "aggs": [1, 2], "maxagg": 2, "perf": 267.1304347826087}, "(app_10, c6i_m6i_r6i)": {"cores": 4000.0, "mem": [6.746301369863015, 6.746301369863015], "aggs": [1, 2], "maxagg": 2, "perf": 614.4}, "(app_11, c6i_m6i_r6i)": {"cores": 4000.0, "mem": [5.81868493150685, 5.81868493150685], "aggs": [1, 2], "maxagg": 2, "perf": 3506.0869565217395}, "(app_12, c6i_m6i_r6i)": {"cores": 4000.0, "mem": [4.553753424657535, 4.553753424657535], "aggs": [1, 2], "maxagg": 2, "perf": 682.6666666666666}, "(app_13, c6i_m6i_r6i)": {"cores": 4000.0, "mem": [5.059726027397261, 5.059726027397261], "aggs": [1, 2], "maxagg": 2, "perf": 2048.0000000000005}, "(app_14, c6i_m6i_r6i)": {"cores": 4000.0, "mem": [6.071671232876713, 6.071671232876713], "aggs": [1, 2], "maxagg": 2, "perf": 2048.0000000000005}, "(app_0, c6g_m6g_r6g)": {"cores": 4000.0, "mem": [3.375, 3.375], "aggs": [1, 2], "maxagg": 2, "perf": 76.8}, "(app_1, c6g_m6g_r6g)": {"cores": 4000.0, "mem": [4.859999999999999, 4.859999999999999], "aggs": [1, 2], "maxagg": 2, "perf": 256.00000000000006}, "(app_2, c6g_m6g_r6g)": {"cores": 4000.0, "mem": [6.21, 6.21], "aggs": [1, 2], "maxagg": 2, "perf": 1335.6521739130437}, "(app_3, c6g_m6g_r6g)": {"cores": 4000.0, "mem": [4.859999999999999, 4.859999999999999], "aggs": [1, 2], "maxagg": 2, "perf": 1760.0000000000005}, "(app_4, c6g_m6g_r6g)": {"cores": 4000.0, "mem": [4.050000000000001, 4.050000000000001], "aggs": [1, 2], "maxagg": 2, "perf": 853.3333333333333}, "(app_5, c6g_m6g_r6g)": {"cores": 4000.0, "mem": [3.375, 3.375], "aggs": [1, 2], "maxagg": 2, "perf": 768.0000000000001}, "(app_6, c6g_m6g_r6g)": {"cores": 4000.0, "mem": [5.175, 5.175], "aggs": [1, 2], "maxagg": 2, "perf": 667.8260869565219}, "(app_7, c6g_m6g_r6g)": {"cores": 2000.0, "mem": [2.53125, 2.53125], "aggs": [1, 2], "maxagg": 2, "perf": 204.8}, "(app_8, c6g_m6g_r6g)": {"cores": 4000.0, "mem": [4.050000000000001, 4.050000000000001], "aggs": [1, 2], "maxagg": 2, "perf": 341.3333333333333}, "(app_9, c6g_m6g_r6g)": {"cores": 4000.0, "mem": [5.951249999999999, 5.951249999999999], "aggs": [1, 2], "maxagg": 2, "perf": 3506.08695652174}, "(app_10, c6g_m6g_r6g)": {"cores": 2000.0, "mem": [2.53125, 2.53125], "aggs": [1, 2], "maxagg": 2, "perf": 1408.0000000000002}, "(app_11, c6g_m6g_r6g)": {"cores": 4000.0, "mem": [4.05, 4.05], "aggs": [1, 2], "maxagg": 2, "perf": 153.6}, "(app_12, c6g_m6g_r6g)": {"cores": 4000.0, "mem": [4.05, 4.05], "aggs": [1, 2], "maxagg": 2, "perf": 307.2}, "(app_13, c6g_m6g_r6g)": {"cores": 4000.0, "mem": [5.175, 5.175], "aggs": [1, 2], "maxagg": 2, "perf": 1335.6521739130437}, "(app_14, c6g_m6g_r6g)": {"cores": 4000.0, "mem": [5.951249999999999, 5.951249999999999], "aggs": [1, 2], "maxagg": 2, "perf": 3506.08695652174}, "(app_0, c7a_m7a_r7a)": {"cores": 8000.0, "mem": [12.490323287671231, 12.490323287671231], "aggs": [1, 2], "maxagg": 2, "perf": 512.0}, "(app_1, c7a_m7a_r7a)": {"cores": 8000.0, "mem": [10.772903835616438, 10.772903835616438], "aggs": [1, 2], "maxagg": 2, "perf": 4693.333333333334}, "(app_2, c7a_m7a_r7a)": {"cores": 8000.0, "mem": [14.363871780821915, 14.363871780821915], "aggs": [1, 2], "maxagg": 2, "perf": 12800.000000000002}, "(app_3, c7a_m7a_r7a)": {"cores": 8000.0, "mem": [14.363871780821915, 14.363871780821915], "aggs": [1, 2], "maxagg": 2, "perf": 12800.000000000002}, "(app_4, c7a_m7a_r7a)": {"cores": 8000.0, "mem": [11.241290958904107, 11.241290958904107], "aggs": [1, 2], "maxagg": 2, "perf": 3520.000000000001}, "(app_5, c7a_m7a_r7a)": {"cores": 3999.9999999999995, "mem": [9.367742465753423, 9.367742465753423], "aggs": [1, 2], "maxagg": 2, "perf": 2816.0000000000005}, "(app_6, c7a_m7a_r7a)": {"cores": 8000.0, "mem": [14.988387945205476, 14.988387945205476], "aggs": [1, 2], "maxagg": 2, "perf": 1024.0}, "(app_7, c7a_m7a_r7a)": {"cores": 3999.9999999999995, "mem": [7.025806849315068, 7.025806849315068], "aggs": [1, 2], "maxagg": 2, "perf": 2048.0}, "(app_8, c7a_m7a_r7a)": {"cores": 3999.9999999999995, "mem": [7.025806849315068, 7.025806849315068], "aggs": [1, 2], "maxagg": 2, "perf": 102.39999999999999}, "(app_9, c7a_m7a_r7a)": {"cores": 8000.0, "mem": [12.490323287671231, 12.490323287671231], "aggs": [1, 2], "maxagg": 2, "perf": 8064.000000000002}, "(app_10, c7a_m7a_r7a)": {"cores": 8000.0, "mem": [7.025806849315069, 7.025806849315069], "aggs": [1, 2], "maxagg": 2, "perf": 170.66666666666666}, "(app_11, c7a_m7a_r7a)": {"cores": 8000.0, "mem": [10.408602739726026, 10.408602739726026], "aggs": [1, 2], "maxagg": 2, "perf": 614.4000000000001}, "(app_12, c7a_m7a_r7a)": {"cores": 8000.0, "mem": [11.96989315068493, 11.96989315068493], "aggs": [1, 2], "maxagg": 2, "perf": 614.4000000000001}, "(app_13, c7a_m7a_r7a)": {"cores": 8000.0, "mem": [14.363871780821915, 14.363871780821915], "aggs": [1, 2], "maxagg": 2, "perf": 1024.0}, "(app_14, c7a_m7a_r7a)": {"cores": 8000.0, "mem": [8.430968219178082, 8.430968219178082], "aggs": [1, 2], "maxagg": 2, "perf": 170.66666666666666}}}, "workloads": {"app_0": 3600.0, "app_1": 3600.0, "app_2": 3600.0, "app_3": 3600.0, "app_4": 3600.0, "app_5": 3600.0, "app_6": 3600.0, "app_7": 3600.0, "app_8": 3600.0, "app_9": 3600.0, "app_10": 3600.0, "app_11": 3600.0, "app_12": 3600.0, "app_13": 3600.0, "app_14": 3600.0}}